databricks_google_sheets
