Metadata-Version: 2.1
Name: databricks-google-sheets
Version: 0.4.0
Summary: Interact with Google Sheets from Databricks
Home-page: https://github.com/vbalasu/databricks-google-sheets
Author: Vijay Balasubramaniam
Author-email: vbalasu@gmail.com
Classifier: Programming Language :: Python :: 3
Classifier: License :: OSI Approved :: MIT License
Classifier: Operating System :: OS Independent
Requires-Python: >=3.6
